README
setup.py
warm/__init__.py
warm/utils.py
warm/version.py
warm.egg-info/PKG-INFO
warm.egg-info/SOURCES.txt
warm.egg-info/dependency_links.txt
warm.egg-info/entry_points.txt
warm.egg-info/requires.txt
warm.egg-info/top_level.txt
warm/components/__init__.py