Metadata-Version: 1.1
Name: warm
Version: 0.2.2
Summary: Deploy a simple OpenStack environment from template
Home-page: https://github.com/sahid/warm.git
Author: Sahid Orentino Ferdjaoui (Cloudwatt)
Author-email: sahid.ferdjaoui@cloudwatt.com
License: Apache License 2.0
Keywords: openstack,cloudwatt,deploy,cloud
Platform: UNKNOWN
Classifier: Development Status :: 4 - Beta
Classifier: Intended Audience :: Developers
Classifier: License :: OSI Approved :: Apache Software License
Classifier: Natural Language :: English
Classifier: Operating System :: MacOS :: MacOS X
Classifier: Operating System :: POSIX :: Linux
Classifier: Programming Language :: Python
Classifier: Environment :: OpenStack
